odoo/addons/sm_report_data/__init__.py
odoo/addons/sm_report_data/__manifest__.py
odoo/addons/sm_report_data/models/__init__.py
odoo/addons/sm_report_data/models/model_reports_cron.py
odoo/addons/sm_report_data/models/models_report_configuration.py
odoo/addons/sm_report_data/models/report_helper.py
odoo/addons/sm_report_data/reports/__init__.py
odoo/addons/sm_report_data/reports/mossos_report.py
odoo/addons/sm_report_data/security/ir.model.access.csv
odoo/addons/sm_report_data/views/templates.xml
odoo/addons/sm_report_data/views/views.xml
odoo/addons/sm_report_data/views/views_report_configuration.xml
odoo12_addon_sm_report_data-12.0.0.0.6.dist-info/METADATA
odoo12_addon_sm_report_data-12.0.0.0.6.dist-info/WHEEL
odoo12_addon_sm_report_data-12.0.0.0.6.dist-info/top_level.txt
odoo12_addon_sm_report_data-12.0.0.0.6.dist-info/RECORD
